{
  "generated": "2026-05-18T14:49:57.730Z",
  "count": 14,
  "projects": [
    {
      "id": "ehe-design-studio",
      "title": "EHE DESIGN STUDIO",
      "category": "WEB DESIGN",
      "description": "Full website design and development for EHE Design Studio — layout, visual identity, and UI.",
      "link": "https://ehedesignstudio.com/",
      "featured": true,
      "order": 1,
      "image": "/images/EHE-1024x509.jpg"
    },
    {
      "id": "refuel-eg-idea",
      "title": "REFUEL.EG + IDEA",
      "category": "VISUAL EFFECTS",
      "description": "Cinematic VFX reel created for the Refuel.EG campaign featuring AI-enhanced motion compositing.",
      "link": "https://www.instagram.com/reel/C_kyJWZCxi_/",
      "featured": true,
      "order": 2,
      "image": "/images/Screenshot_10.jpg"
    },
    {
      "id": "guitar-on-fire",
      "title": "GUITAR ON FIRE",
      "category": "VISUAL EFFECTS + AI",
      "description": "AI-powered fire compositing on a guitar performance — pushing the limits of creative VFX.",
      "link": "https://www.instagram.com/reel/C_0hMXpinbO/",
      "featured": true,
      "order": 3,
      "image": "/images/Screenshot_12-852x1024.jpg"
    },
    {
      "id": "ehe-design-studio-v2",
      "title": "EHE DESIGN STUDIO V2",
      "category": "WEB DESIGN",
      "description": "Redesign iteration for EHE Design Studio with improved layout and visual refinements.",
      "link": "#",
      "featured": false,
      "order": 4,
      "image": "/images/Screenshot_9-1024x601.jpg"
    },
    {
      "id": "visual-reel",
      "title": "VISUAL REEL",
      "category": "VISUAL EFFECTS",
      "description": "A showcase reel of motion graphics and visual effects work across multiple projects.",
      "link": "#",
      "featured": true,
      "order": 5,
      "image": "/images/Screenshot_8.jpg"
    },
    {
      "id": "portrait-session",
      "title": "PORTRAIT SESSION",
      "category": "PHOTOGRAPHY",
      "description": "High-end portrait photography with creative lighting and post-processing.",
      "link": "#",
      "featured": false,
      "order": 6,
      "image": "/images/Screenshot_11.jpg"
    },
    {
      "id": "creative-edit",
      "title": "CREATIVE EDIT",
      "category": "PHOTO EDITING",
      "description": "Creative photo manipulation and compositing for social media content.",
      "link": "#",
      "featured": false,
      "order": 7,
      "image": "/images/Screenshot_14.jpg"
    },
    {
      "id": "motion-reel",
      "title": "MOTION REEL",
      "category": "MOTION DESIGN",
      "description": "Dynamic motion design reel featuring kinetic typography and animated brand elements.",
      "link": "#",
      "featured": false,
      "order": 8,
      "image": "/images/Screenshot_13-1024x576.jpg"
    },
    {
      "id": "strike-egypt-stronger",
      "title": "STRIKE EGYPT: STRONGER TOGETHER",
      "category": "MOTION DESIGN",
      "description": "Stronger together, one punch at a time. High-energy promotional reel for Strike Egypt boxing gym.",
      "link": "https://www.instagram.com/reel/DBvzw3BI2lF/?igsh=MWVmdDVoMTBmY2Uxdw==",
      "featured": true,
      "order": 9,
      "image": "/images/STRONGER TOGETHER.jpg"
    },
    {
      "id": "strike-egypt-coach-shady",
      "title": "STRIKE EGYPT: COACH SHADY",
      "category": "MOTION DESIGN",
      "description": "Meet Coach Shady at Strike. Fast-paced promotional profile reel showcasing boxing expertise and training intensity.",
      "link": "https://www.instagram.com/reel/DBwBkD4I0zl/?igsh=NTkza3R2enV0NGdv",
      "featured": false,
      "order": 10,
      "image": "/images/COACH SHADY.jpg"
    },
    {
      "id": "strike-egypt-unleash",
      "title": "STRIKE EGYPT: UNLEASH YOUR STRENGTH",
      "category": "MOTION DESIGN",
      "description": "Ready to unleash your strength? Cinematic promotional edit for Strike Egypt highlighting the unique boxing experience.",
      "link": "https://www.instagram.com/reel/DCIAkqboLzO/?igsh=MTRpeno4dTdvejhtaA==",
      "featured": false,
      "order": 11,
      "image": "/images/UNLEASH YOUR STRENGTH.jpg"
    },
    {
      "id": "strike-egypt-kids",
      "title": "STRIKE EGYPT: KIDS KICKSTARTER",
      "category": "MOTION DESIGN",
      "description": "Kids Kickstarter Program promo video. Engaging visual content designed to inspire the next generation of martial artists.",
      "link": "https://www.instagram.com/reel/DCuA5YxIX8I/?igsh=Y21oNXM2aTlwOXdq",
      "featured": false,
      "order": 12,
      "image": "/images/KIDS KICKSTARTER.jpg"
    },
    {
      "id": "strike-egypt-action",
      "title": "STRIKE EGYPT: JUST ACTION",
      "category": "MOTION DESIGN",
      "description": "No Excuses. Just Action. Impactful and dynamic reel driving motivation and engagement for Strike Egypt.",
      "link": "https://www.instagram.com/reel/DDcO7HCoBru/?igsh=OGE1dTZ2MGw5bnpl",
      "featured": false,
      "order": 13,
      "image": "/images/JUST ACTION.jpg"
    },
    {
      "id": "strike-egypt-together",
      "title": "STRIKE EGYPT: STRIKING TOGETHER",
      "category": "MOTION DESIGN",
      "description": "Striking together, stronger together. A sleek, high-tempo visual edit capturing the community and energy of Strike.",
      "link": "https://www.instagram.com/reel/DDr0tXtgqJm/?igsh=dzZ3d214YXgwenJ5",
      "featured": false,
      "order": 14,
      "image": "/images/JUST STRIKING.jpg"
    }
  ]
}